{
"categories":[
    {
        "href": "all",
        "name": "все",
        "category_is_active": True
    },
    {
        "href": "home",
        "name": "дом",
        "category_is_active": True
    },
    {
        "href": "office",
        "name": "офис",
        "category_is_active": True
    },
    {
        "href": "modern",
        "name": "модерн",
        "category_is_active": True

    },
    {
        "href": "classic",
        "name": "классика",
        "category_is_active": True
    }
]
}